elora/__init__.py
elora/const.py
elora/main.py
elora/assets/dims/Llama3-70B-it.json
elora/assets/dims/Llama3-70B.json
elora/assets/dims/Llama3-8B-it.json
elora/assets/dims/Llama3-8B.json
elora/assets/dims/Llama3.1-405B-it.json
elora/assets/dims/Llama3.1-70B-it.json
elora/assets/dims/Llama3.1-70B.json
elora/assets/dims/Llama3.1-8B-it.json
elora/assets/dims/Llama3.1-8B.json
elora/assets/dims/Llama3.2-1B-it.json
elora/assets/dims/Llama3.2-1B.json
elora/assets/dims/Llama3.2-3B-it.json
elora/assets/dims/Llama3.2-3B.json
elora/assets/scores/self/Llama3-8B/effective_rank.json
elora/assets/scores/self/Llama3-8B/frobenius_norm.json
elora/assets/scores/self/Llama3-8B/nuclear_norm.json
elora/assets/scores/self/Llama3-8B/nuclear_stable_rank.json
elora/assets/scores/self/Llama3-8B/spectral_norm.json
elora/assets/scores/self/Llama3-8B/stable_rank.json
elora/assets/scores/self/Llama3-8B-it/effective_rank.json
elora/assets/scores/self/Llama3-8B-it/frobenius_norm.json
elora/assets/scores/self/Llama3-8B-it/nuclear_norm.json
elora/assets/scores/self/Llama3-8B-it/nuclear_stable_rank.json
elora/assets/scores/self/Llama3-8B-it/spectral_norm.json
elora/assets/scores/self/Llama3-8B-it/stable_rank.json
elora/assets/scores/self/Llama3.1-8B/effective_rank.json
elora/assets/scores/self/Llama3.1-8B/frobenius_norm.json
elora/assets/scores/self/Llama3.1-8B/nuclear_norm.json
elora/assets/scores/self/Llama3.1-8B/nuclear_stable_rank.json
elora/assets/scores/self/Llama3.1-8B/spectral_norm.json
elora/assets/scores/self/Llama3.1-8B/stable_rank.json
elora/assets/scores/self/Llama3.1-8B-it/effective_rank.json
elora/assets/scores/self/Llama3.1-8B-it/frobenius_norm.json
elora/assets/scores/self/Llama3.1-8B-it/nuclear_norm.json
elora/assets/scores/self/Llama3.1-8B-it/nuclear_stable_rank.json
elora/assets/scores/self/Llama3.1-8B-it/spectral_norm.json
elora/assets/scores/self/Llama3.1-8B-it/stable_rank.json
elora/assets/scores/self/Llama3.2-1B/effective_rank.json
elora-0.0.9.dist-info/LICENSE
elora-0.0.9.dist-info/METADATA
elora-0.0.9.dist-info/WHEEL
elora-0.0.9.dist-info/top_level.txt
elora-0.0.9.dist-info/RECORD
