Metadata-Version: 2.2
Name: elora
Version: 0.0.9
Summary: eLoRA: Efficient Low-Rank Allocation for Budget-Constrained Fine-Tuning 🧮💰⚙️🎛️
Author-email: Mohsen Hariri <mohsen.hariri@case.edu>
License: GPL-3.0 License
Keywords: Large Language Models,Fine-Tuning,LoRA
Classifier: Programming Language :: Python :: 3.10
Classifier: License :: OSI Approved :: GNU General Public License v3 or later (GPLv3+)
Classifier: Operating System :: OS Independent
Requires-Python: >=3.10
License-File: LICENSE
Requires-Dist: importlib-metadata; python_version < "3.8"
